[
    {
        "title": "Frontend Developer",
        "company": "FPT Polytechnic College",
        "date": "Aug 2023 - Present (Freelancer)",
        "description": "Collaborated with other engineers to design, build, and develop projects for clients of FPT Polytechnic College. Developed a web application to manage students and activities in a workshop setting, successfully managing ~10,000 registered students and more than 477 projects.",
        "skills": [
            "REST APIs",
            "TypeScript",
            "React",
            "Tailwind CSS",
            "RTK Query",
            "Redux toolkit",
            "JWT",
            "NestJs",
            "MongoDB",
            "Docker",
            "I18n",
            "Zod",
            "React Query",
            "Socket.io",
            "CSS Framework",
            "Cloudinary",
            "Clerk",
            "Strapi",
            "Framer-motion",
            "Stripe",
            "Firebase"
        ]
    },
    {
        "title": "Backend Developer",
        "company": "TIEN PHONG CDS JOINT STOCK COMPANY",
        "date": "December 2023 - June 2023 · 6 mos",
        "description": "I have experience in maintaining and improving performance to meet client requirements. Collaborated with other engineers to design reliable and scalable API solutions and ensured high availability and responsiveness through testing and troubleshooting.",
        "skills": [
            "Full Stack Development",
            "PHP",
            "Laravel Lumen",
            "MySQL",
            "PostgreSQL",
            "Ruby on Rails",
            "Packaging Design",
            "Figma",
            "Ant design",
            "Postman API",
            "Design Patterns"
        ]
    },
    {
        "title": "Developer",
        "company": "Bytez Team",
        "date": "August 2024 - Present",
        "description": "Designed and developed a software, Collaborated with other engineers on existing internal systems to implement feature enhancements and modifications.",
        "skills": [
            "TypeScript",
            "Nextjs",
            "Laravel Lumen",
            "MySQL",
            "PostgreSQL",
            "Ruby on Rails",
            "Packaging Design",
            "Figma",
            "Ant design",
            "Postman API",
            "Design Patterns"
        ]
    }
]
